cyberrangecz/cloud_commons/__init__.py
cyberrangecz/cloud_commons/cloud_client_base.py
cyberrangecz/cloud_commons/cloud_client_elements.py
cyberrangecz/cloud_commons/exceptions.py
cyberrangecz/cloud_commons/topology_elements.py
cyberrangecz/cloud_commons/topology_instance.py
cyberrangecz/cloud_commons/transformation_configuration.py
cyberrangecz_python_commons-0.1.17.dist-info/METADATA
cyberrangecz_python_commons-0.1.17.dist-info/WHEEL
cyberrangecz_python_commons-0.1.17.dist-info/top_level.txt
cyberrangecz_python_commons-0.1.17.dist-info/RECORD
