Metadata-Version: 2.1
Name: cyberrangecz-python-commons
Version: 0.1.17
Summary: Python Commons
Author: cybersecurityhub.cz
Requires-Python: >=3
Requires-Dist: cyberrangecz-topology-definition~=0.5.11
